m3_gar/__init__.py
m3_gar/base_models.py
m3_gar/compat.py
m3_gar/config.py
m3_gar/consts.py
m3_gar/enums.py
m3_gar/exceptions.py
m3_gar/publish_tools.py
m3_gar/routers.py
m3_gar/util.py
m3_gar/version.py
m3_gar/importer/__init__.py
m3_gar/importer/client.py
m3_gar/importer/commands.py
m3_gar/importer/constraints.py
m3_gar/importer/consts.py
m3_gar/importer/db_wrapper.py
m3_gar/importer/exceptions.py
m3_gar/importer/loader.py
m3_gar/importer/models_sort.py
m3_gar/importer/signals.py
m3_gar/importer/timer.py
m3_gar/importer/version.py
m3_gar/importer/source/__init__.py
m3_gar/importer/source/archive.py
m3_gar/importer/source/directory.py
m3_gar/importer/source/exceptions.py
m3_gar/importer/source/tablelist.py
m3_gar/importer/source/wrapper.py
m3_gar/importer/table/__init__.py
m3_gar/importer/table/consts.py
m3_gar/importer/table/exceptions.py
m3_gar/importer/table/table.py
m3_gar/importer/table/xml.py
m3_gar/management/__init__.py
m3_gar/management/commands/__init__.py
m3_gar/management/commands/fill_custom_fields.py
m3_gar/management/commands/gar_check_models.py
m3_gar/management/commands/gar_generate_base_models.py
m3_gar/management/commands/gar_load_data.py
m3_gar/management/commands/gar_update_schema.py
m3_gar/management/commands/manage_constraints.py
m3_gar/migrations/0001_initial.py
m3_gar/migrations/0002_auto_20210707_1352.py
m3_gar/migrations/0003_auto_20210906_0744.py
m3_gar/migrations/0004_auto_20211013_1106.py
m3_gar/migrations/0005_auto_20211029_1212.py
m3_gar/migrations/0006_auto_20211105_0937.py
m3_gar/migrations/0007_version_processed.py
m3_gar/migrations/0008_auto_20220217_0556.py
m3_gar/migrations/0009_delete_status.py
m3_gar/migrations/0010_auto_20220225_0934.py
m3_gar/migrations/0011_auto_20220323_1022.py
m3_gar/migrations/0012_auto_20220415_1452.py
m3_gar/migrations/0013_auto_20220513_0825.py
m3_gar/migrations/0014_addrobj_name_with_typename.py
m3_gar/migrations/0015_alter_normativedocs_orgname.py
m3_gar-1.1.6.dist-info/METADATA
m3_gar-1.1.6.dist-info/WHEEL
m3_gar-1.1.6.dist-info/top_level.txt
m3_gar-1.1.6.dist-info/RECORD
