Metadata-Version: 2.4
Name: m3-gar
Version: 1.1.6
Summary: GAR Django integration for m3
Author: BARS Group
Author-email: bars@bars.group
License: MIT license
Classifier: Development Status :: 4 - Beta
Classifier: Intended Audience :: Developers
Classifier: Intended Audience :: Science/Research
Classifier: License :: OSI Approved :: MIT License
Classifier: Natural Language :: Russian
Classifier: Programming Language :: Python
Classifier: Programming Language :: Python :: 3
Classifier: Programming Language :: Python :: 3.9
Classifier: Topic :: Software Development :: Libraries :: Python Modules
Requires-Dist: Django>=3.2
Requires-Dist: requests
Requires-Dist: lxml
Requires-Dist: progress
Requires-Dist: gitpython
Requires-Dist: twine
Requires-Dist: asyncpg
Requires-Dist: uvloop
Requires-Dist: django-cte==1.1.5
Requires-Dist: m3-gar-constants>=1.0.4
Dynamic: author
Dynamic: author-email
Dynamic: classifier
Dynamic: description
Dynamic: license
Dynamic: requires-dist
Dynamic: summary
